[{"name":"Episode III","artists":"Charlie Burg","album":"Live in Peter's Attic","id":"0MgGlkUVqyNVFYu3sZ4LyA","time":"2023-02-19T06:30:50Z","addedBy":"12121954989"},{"name":"Lovesong (The Way) [feat. Bluets]","artists":"Charlie Burg, Bluets","album":"One, Violet","id":"4JkKXuKp2RdbE5M7L4z19Z","time":"2023-02-19T06:33:35Z","addedBy":"12121954989"},{"name":"Channel Orange In Your Living Room","artists":"Charlie Burg","album":"Channel Orange In Your Living Room","id":"27AJf1VXuh3h6QsqQBOLxf","time":"2023-02-19T06:40:42Z","addedBy":"12121954989"},{"name":"Sweet Dreams, Sweet Heart","artists":"Ben Chandler","album":"Sweet Dreams, Sweet Heart EP","id":"2J9glVQyozhwWGSlBjbeq3","time":"2023-02-19T07:15:00Z","addedBy":"12121954989"}]